djangoldp_hiphopcommunity/__init__.py
djangoldp_hiphopcommunity/admin.py
djangoldp_hiphopcommunity/apps.py
djangoldp_hiphopcommunity/context_processors.py
djangoldp_hiphopcommunity/djangoldp_settings.py
djangoldp_hiphopcommunity/filters.py
djangoldp_hiphopcommunity/forms.py
djangoldp_hiphopcommunity/models.py
djangoldp_hiphopcommunity/permissions.py
djangoldp_hiphopcommunity/settings.py
djangoldp_hiphopcommunity/tests.py
djangoldp_hiphopcommunity/views.py
djangoldp_hiphopcommunity/migrations/0001_initial.py
djangoldp_hiphopcommunity/migrations/0002_member.py
djangoldp_hiphopcommunity/migrations/0003_auto_20220208_1727.py
djangoldp_hiphopcommunity/migrations/0004_partner_partnertype.py
djangoldp_hiphopcommunity/migrations/0005_auto_20220210_1219.py
djangoldp_hiphopcommunity/migrations/0006_campain_tool.py
djangoldp_hiphopcommunity/migrations/0007_premium.py
djangoldp_hiphopcommunity/migrations/0008_auto_20220224_2037.py
djangoldp_hiphopcommunity/migrations/0009_auto_20220225_1154.py
djangoldp_hiphopcommunity/migrations/0010_auto_20220225_1200.py
djangoldp_hiphopcommunity/migrations/0011_auto_20220228_1458.py
djangoldp_hiphopcommunity/migrations/0012_auto_20220303_1046.py
djangoldp_hiphopcommunity/migrations/0013_auto_20220303_1054.py
djangoldp_hiphopcommunity/migrations/0014_auto_20220303_1104.py
djangoldp_hiphopcommunity/migrations/0015_hiphopusersettings.py
djangoldp_hiphopcommunity/migrations/0016_auto_20220426_1609.py
djangoldp_hiphopcommunity/migrations/0017_auto_20220503_2205.py
djangoldp_hiphopcommunity/migrations/0018_auto_20220606_0302.py
djangoldp_hiphopcommunity/migrations/0019_auto_20220610_1321.py
djangoldp_hiphopcommunity/migrations/0020_auto_20220610_1420.py
djangoldp_hiphopcommunity/migrations/0021_auto_20220614_1825.py
djangoldp_hiphopcommunity/migrations/__init__.py
djangoldp_hiphopcommunity/static/css/registration.css
djangoldp_hiphopcommunity/static/img/chevron.svg
djangoldp_hiphopcommunity/static/img/chevron_white.png
djangoldp_hiphopcommunity-0.0.23.dist-info/METADATA
djangoldp_hiphopcommunity-0.0.23.dist-info/WHEEL
djangoldp_hiphopcommunity-0.0.23.dist-info/top_level.txt
djangoldp_hiphopcommunity-0.0.23.dist-info/RECORD
