Metadata-Version: 2.1
Name: djangoldp-hiphopcommunity
Version: 0.0.23
Summary: {{ description }}
Home-page: UNKNOWN
License: MIT
Platform: UNKNOWN
Classifier: Programming Language :: Python :: 3
Requires-Dist: djangoldp (>=2.1)
